<signatures>
<Signature xmlns="http://www.w3.org/2000/09/xmldsig#" Id="PackageSignature">
<SignedInfo>
<CanonicalizationMethod Algorithm="http://www.w3.org/TR/2001/REC-xml-c14n-20010315"></CanonicalizationMethod>
<SignatureMethod Algorithm="http://www.w3.org/2000/09/xmldsig#rsa-sha1"></SignatureMethod>
<Reference URI="#PackageContents">
<Transforms>
<Transform Algorithm="http://www.w3.org/TR/2001/REC-xml-c14n-20010315"></Transform>
</Transforms>
<DigestMethod Algorithm="http://www.w3.org/2001/04/xmlenc#sha256"></DigestMethod>
<DigestValue>{0}</DigestValue>
</Reference>
</SignedInfo>
<SignatureValue Id="PackageSignatureValue">
{1}
</SignatureValue>
<KeyInfo>
<X509Data>
</X509Data>
</KeyInfo>
<Object>
<Manifest Id="PackageContents">
</Manifest>
</Object>
</Signature>
</signatures>
